nestbackup.py
nestbackup-0.0.4.dist-info/LICENSE
nestbackup-0.0.4.dist-info/METADATA
nestbackup-0.0.4.dist-info/WHEEL
nestbackup-0.0.4.dist-info/entry_points.txt
nestbackup-0.0.4.dist-info/top_level.txt
nestbackup-0.0.4.dist-info/RECORD
