Metadata-Version: 2.1
Name: nestbackup
Version: 0.0.4
Summary: Backup a server to S3 using a short and simple config file.
Home-page: https://github.com/jorgebg/nestbackup
Author: Jorge Barata
Author-email: jorge.barata.gonzalez@gmail.com
License: MIT
Platform: UNKNOWN
Classifier: License :: OSI Approved :: MIT License
Classifier: Programming Language :: Python
Classifier: Programming Language :: Python :: 3
Classifier: Programming Language :: Python :: 3.6
Classifier: Programming Language :: Python :: Implementation :: CPython
Classifier: Programming Language :: Python :: Implementation :: PyPy
Classifier: Topic :: System :: Archiving :: Backup
Requires-Python: >=3.6.0
License-File: LICENSE
